Alert_System.py
Alert_System_for_Face_and_Pose-0.1.0.dist-info/METADATA
Alert_System_for_Face_and_Pose-0.1.0.dist-info/WHEEL
Alert_System_for_Face_and_Pose-0.1.0.dist-info/entry_points.txt
Alert_System_for_Face_and_Pose-0.1.0.dist-info/top_level.txt
Alert_System_for_Face_and_Pose-0.1.0.dist-info/RECORD
